{
    "/js/app.js": "/js/app.js",
    "/css/app.css": "/css/app.css",
    "/0.18b47a58352acb73194a.hot-update.js": "/0.18b47a58352acb73194a.hot-update.js",
    "/0.8eeca14562640ce9c26f.hot-update.js": "/0.8eeca14562640ce9c26f.hot-update.js",
    "/0.818b663aef3604054457.hot-update.js": "/0.818b663aef3604054457.hot-update.js",
    "/0.12935de0bca93830150e.hot-update.js": "/0.12935de0bca93830150e.hot-update.js",
    "/0.df7e4c38c754d6ca65c8.hot-update.js": "/0.df7e4c38c754d6ca65c8.hot-update.js",
    "/0.0173dc685888db908812.hot-update.js": "/0.0173dc685888db908812.hot-update.js",
    "/0.7b42032d55e787b31834.hot-update.js": "/0.7b42032d55e787b31834.hot-update.js",
    "/0.c9cab6e0055f5e0e6dcd.hot-update.js": "/0.c9cab6e0055f5e0e6dcd.hot-update.js",
    "/0.496e871251016c39bf25.hot-update.js": "/0.496e871251016c39bf25.hot-update.js",
    "/0.d3c54b583d3ff06f4f4c.hot-update.js": "/0.d3c54b583d3ff06f4f4c.hot-update.js",
    "/0.4605b53069b94fc91f15.hot-update.js": "/0.4605b53069b94fc91f15.hot-update.js",
    "/0.ea2b8a0adf37a50e96b1.hot-update.js": "/0.ea2b8a0adf37a50e96b1.hot-update.js",
    "/0.0dd0e8fdff5179aeb7b1.hot-update.js": "/0.0dd0e8fdff5179aeb7b1.hot-update.js",
    "/0.c234dd6d6c50cc4b963e.hot-update.js": "/0.c234dd6d6c50cc4b963e.hot-update.js",
    "/0.947342c0af8ab609f0be.hot-update.js": "/0.947342c0af8ab609f0be.hot-update.js",
    "/0.63e5340ed0e461d2c9f5.hot-update.js": "/0.63e5340ed0e461d2c9f5.hot-update.js",
    "/0.416e1a09eac718419454.hot-update.js": "/0.416e1a09eac718419454.hot-update.js",
    "/0.2cd7f36e083f571300c3.hot-update.js": "/0.2cd7f36e083f571300c3.hot-update.js",
    "/0.1791120ba8b0ee45a78c.hot-update.js": "/0.1791120ba8b0ee45a78c.hot-update.js",
    "/0.492b75b03a7d5dfd3e5d.hot-update.js": "/0.492b75b03a7d5dfd3e5d.hot-update.js",
    "/0.4ec6472aef984e407fdf.hot-update.js": "/0.4ec6472aef984e407fdf.hot-update.js",
    "/0.9c0537a3700d5c779351.hot-update.js": "/0.9c0537a3700d5c779351.hot-update.js",
    "/0.ce9cfa87cafdb214320b.hot-update.js": "/0.ce9cfa87cafdb214320b.hot-update.js",
    "/0.9189347f8d6d1fd05ffc.hot-update.js": "/0.9189347f8d6d1fd05ffc.hot-update.js",
    "/0.78942aa9380897f6c58a.hot-update.js": "/0.78942aa9380897f6c58a.hot-update.js",
    "/0.0d45335c79e45afdc74f.hot-update.js": "/0.0d45335c79e45afdc74f.hot-update.js",
    "/0.0b3e434bdbaa31d8229b.hot-update.js": "/0.0b3e434bdbaa31d8229b.hot-update.js",
    "/0.035b759e6bfa2ecaae3a.hot-update.js": "/0.035b759e6bfa2ecaae3a.hot-update.js",
    "/0.071156d8a0501ff6c181.hot-update.js": "/0.071156d8a0501ff6c181.hot-update.js",
    "/0.e338c59e6ed691c0a47a.hot-update.js": "/0.e338c59e6ed691c0a47a.hot-update.js",
    "/0.2b7467ff8331d16b7911.hot-update.js": "/0.2b7467ff8331d16b7911.hot-update.js",
    "/0.91d7e2d1141b6781af6a.hot-update.js": "/0.91d7e2d1141b6781af6a.hot-update.js",
    "/0.4541b5e2b9b85b6b7d4e.hot-update.js": "/0.4541b5e2b9b85b6b7d4e.hot-update.js",
    "/0.5f6967231ee705e10314.hot-update.js": "/0.5f6967231ee705e10314.hot-update.js",
    "/0.fedbbf8a50b519b281a3.hot-update.js": "/0.fedbbf8a50b519b281a3.hot-update.js",
    "/0.68a2a3f73a60e2cffa1b.hot-update.js": "/0.68a2a3f73a60e2cffa1b.hot-update.js",
    "/0.1f921207cf8dca1e6fae.hot-update.js": "/0.1f921207cf8dca1e6fae.hot-update.js",
    "/0.ce5c355ef84550725170.hot-update.js": "/0.ce5c355ef84550725170.hot-update.js",
    "/0.6151b6b8296920f3d504.hot-update.js": "/0.6151b6b8296920f3d504.hot-update.js",
    "/0.ac20ce52811ad077e2db.hot-update.js": "/0.ac20ce52811ad077e2db.hot-update.js",
    "/0.beef30145fbcb4c7fbe1.hot-update.js": "/0.beef30145fbcb4c7fbe1.hot-update.js",
    "/0.c94ffc0e87013cc2aead.hot-update.js": "/0.c94ffc0e87013cc2aead.hot-update.js",
    "/0.520b2eb64949ee9db5b0.hot-update.js": "/0.520b2eb64949ee9db5b0.hot-update.js",
    "/0.504148f1d7347c14ede3.hot-update.js": "/0.504148f1d7347c14ede3.hot-update.js",
    "/0.b00f593bb7339ede4f9b.hot-update.js": "/0.b00f593bb7339ede4f9b.hot-update.js",
    "/0.2d6e228d395b7a2b54ed.hot-update.js": "/0.2d6e228d395b7a2b54ed.hot-update.js",
    "/0.bfc22530a64c1c656c40.hot-update.js": "/0.bfc22530a64c1c656c40.hot-update.js",
    "/0.3b6469e0c0675bcf1741.hot-update.js": "/0.3b6469e0c0675bcf1741.hot-update.js",
    "/0.e55f390c3be3541b2cd7.hot-update.js": "/0.e55f390c3be3541b2cd7.hot-update.js",
    "/0.c0c2ac660d97391594b5.hot-update.js": "/0.c0c2ac660d97391594b5.hot-update.js",
    "/0.079f226b02b2b88ce4dd.hot-update.js": "/0.079f226b02b2b88ce4dd.hot-update.js",
    "/0.3310ef9f142c90baf1f9.hot-update.js": "/0.3310ef9f142c90baf1f9.hot-update.js",
    "/0.3878f12ad88d9af2ff2d.hot-update.js": "/0.3878f12ad88d9af2ff2d.hot-update.js",
    "/0.9b261602e76f08fd5c46.hot-update.js": "/0.9b261602e76f08fd5c46.hot-update.js",
    "/0.1137b7c757907666d98a.hot-update.js": "/0.1137b7c757907666d98a.hot-update.js",
    "/0.ce835473cde127bfc2eb.hot-update.js": "/0.ce835473cde127bfc2eb.hot-update.js",
    "/0.cce0f5a9adfcaa45751b.hot-update.js": "/0.cce0f5a9adfcaa45751b.hot-update.js",
    "/0.2ebedcdd1a0ffe6e8805.hot-update.js": "/0.2ebedcdd1a0ffe6e8805.hot-update.js",
    "/0.ebe232f061537d56444d.hot-update.js": "/0.ebe232f061537d56444d.hot-update.js",
    "/0.23ad6cdbaed302ce4f75.hot-update.js": "/0.23ad6cdbaed302ce4f75.hot-update.js",
    "/0.d78b9ef06da9f6fa73e7.hot-update.js": "/0.d78b9ef06da9f6fa73e7.hot-update.js",
    "/0.c9bd90bd446b0c77f999.hot-update.js": "/0.c9bd90bd446b0c77f999.hot-update.js",
    "/0.95cbc50742d4805df177.hot-update.js": "/0.95cbc50742d4805df177.hot-update.js",
    "/0.d9787a7ca6c077a4716e.hot-update.js": "/0.d9787a7ca6c077a4716e.hot-update.js",
    "/0.14374a327a1b350a1806.hot-update.js": "/0.14374a327a1b350a1806.hot-update.js",
    "/0.b637e671f4ba31053060.hot-update.js": "/0.b637e671f4ba31053060.hot-update.js",
    "/0.456da22f250b3abf38fa.hot-update.js": "/0.456da22f250b3abf38fa.hot-update.js",
    "/0.fd1890220e7bb547c3af.hot-update.js": "/0.fd1890220e7bb547c3af.hot-update.js",
    "/0.e8205d434f8b5f70fdc1.hot-update.js": "/0.e8205d434f8b5f70fdc1.hot-update.js",
    "/0.7055b712400e6536ac69.hot-update.js": "/0.7055b712400e6536ac69.hot-update.js",
    "/0.3126624879e2894ac69b.hot-update.js": "/0.3126624879e2894ac69b.hot-update.js",
    "/0.0579ce3cf527fafbe30c.hot-update.js": "/0.0579ce3cf527fafbe30c.hot-update.js",
    "/0.fad636a3c3ae5d9c4c24.hot-update.js": "/0.fad636a3c3ae5d9c4c24.hot-update.js",
    "/0.a1f6b3a1c8088b4fa00a.hot-update.js": "/0.a1f6b3a1c8088b4fa00a.hot-update.js",
    "/0.5476a630886958e94b51.hot-update.js": "/0.5476a630886958e94b51.hot-update.js",
    "/0.818c82cc8000eacd8553.hot-update.js": "/0.818c82cc8000eacd8553.hot-update.js",
    "/0.d667c1a27745b9dca5c1.hot-update.js": "/0.d667c1a27745b9dca5c1.hot-update.js",
    "/0.3b905d86df05edd90bcc.hot-update.js": "/0.3b905d86df05edd90bcc.hot-update.js",
    "/0.3bd7a4394814c0ec40b0.hot-update.js": "/0.3bd7a4394814c0ec40b0.hot-update.js",
    "/0.97c589d8ed6766555c8e.hot-update.js": "/0.97c589d8ed6766555c8e.hot-update.js",
    "/0.79ffd33351dee73ce06f.hot-update.js": "/0.79ffd33351dee73ce06f.hot-update.js",
    "/0.055d665aa8ff8a6a6802.hot-update.js": "/0.055d665aa8ff8a6a6802.hot-update.js",
    "/0.ddbf90abff473fd5d39c.hot-update.js": "/0.ddbf90abff473fd5d39c.hot-update.js",
    "/0.a3007f7d9252e6d7d3ed.hot-update.js": "/0.a3007f7d9252e6d7d3ed.hot-update.js",
    "/0.bf45d132155077654288.hot-update.js": "/0.bf45d132155077654288.hot-update.js",
    "/0.baa2504b17fdfa96c936.hot-update.js": "/0.baa2504b17fdfa96c936.hot-update.js",
    "/0.8001dd07bc2f504380e6.hot-update.js": "/0.8001dd07bc2f504380e6.hot-update.js",
    "/0.1480eccb39643ed05cc6.hot-update.js": "/0.1480eccb39643ed05cc6.hot-update.js",
    "/0.4dec45e04a34505cf9b1.hot-update.js": "/0.4dec45e04a34505cf9b1.hot-update.js",
    "/0.ed90bb4937b80c22aa65.hot-update.js": "/0.ed90bb4937b80c22aa65.hot-update.js",
    "/0.40bbc221e21a7f070db0.hot-update.js": "/0.40bbc221e21a7f070db0.hot-update.js",
    "/0.c9230ec9f5c9c4df3597.hot-update.js": "/0.c9230ec9f5c9c4df3597.hot-update.js",
    "/0.e589a8bc2064c997c111.hot-update.js": "/0.e589a8bc2064c997c111.hot-update.js",
    "/0.0d22dd4d1079d2e8b284.hot-update.js": "/0.0d22dd4d1079d2e8b284.hot-update.js",
    "/0.d6e25c147d9a0a3c3886.hot-update.js": "/0.d6e25c147d9a0a3c3886.hot-update.js"
}