{
    "/js/app.js": "/js/app.js",
    "/css/app.css": "/css/app.css",
    "/0.26e29ea0e9218c3caab3.hot-update.js": "/0.26e29ea0e9218c3caab3.hot-update.js",
    "/0.12fc2469c7fd0b81e7e0.hot-update.js": "/0.12fc2469c7fd0b81e7e0.hot-update.js",
    "/0.716324c057eb131ef09d.hot-update.js": "/0.716324c057eb131ef09d.hot-update.js",
    "/0.4a8f0e068aca15d73497.hot-update.js": "/0.4a8f0e068aca15d73497.hot-update.js",
    "/0.a9dcf8fc91da8a3a7674.hot-update.js": "/0.a9dcf8fc91da8a3a7674.hot-update.js",
    "/0.38bb3f284591c80e5bbe.hot-update.js": "/0.38bb3f284591c80e5bbe.hot-update.js",
    "/0.6a2ace889d0a7a0209ae.hot-update.js": "/0.6a2ace889d0a7a0209ae.hot-update.js",
    "/0.da09985e190268ba5164.hot-update.js": "/0.da09985e190268ba5164.hot-update.js",
    "/0.fdf7751e1710954cc775.hot-update.js": "/0.fdf7751e1710954cc775.hot-update.js",
    "/0.cd20c9cace0b2fae013b.hot-update.js": "/0.cd20c9cace0b2fae013b.hot-update.js",
    "/0.be555cead6a12c5c8837.hot-update.js": "/0.be555cead6a12c5c8837.hot-update.js",
    "/0.610e5dd15cf3776ee4b6.hot-update.js": "/0.610e5dd15cf3776ee4b6.hot-update.js",
    "/0.7e636d4acf09c55dc964.hot-update.js": "/0.7e636d4acf09c55dc964.hot-update.js",
    "/0.107c8e488ed1c07a7c06.hot-update.js": "/0.107c8e488ed1c07a7c06.hot-update.js",
    "/0.1a24208277f25872513d.hot-update.js": "/0.1a24208277f25872513d.hot-update.js",
    "/0.72e73f5576fa7af94d35.hot-update.js": "/0.72e73f5576fa7af94d35.hot-update.js",
    "/0.02e04b619900057479b0.hot-update.js": "/0.02e04b619900057479b0.hot-update.js",
    "/0.0fee7484f0d7c9828dbb.hot-update.js": "/0.0fee7484f0d7c9828dbb.hot-update.js",
    "/0.7ec9435cd9eb40443854.hot-update.js": "/0.7ec9435cd9eb40443854.hot-update.js",
    "/0.e19003fed919000a1383.hot-update.js": "/0.e19003fed919000a1383.hot-update.js",
    "/0.407557e46765fa332b9a.hot-update.js": "/0.407557e46765fa332b9a.hot-update.js",
    "/0.779e341979af74c581bd.hot-update.js": "/0.779e341979af74c581bd.hot-update.js",
    "/0.ca7c9abf5238125e45f9.hot-update.js": "/0.ca7c9abf5238125e45f9.hot-update.js",
    "/0.e5aa4c8c27c6f469a65f.hot-update.js": "/0.e5aa4c8c27c6f469a65f.hot-update.js",
    "/0.11ad65c8018c22e3dfc7.hot-update.js": "/0.11ad65c8018c22e3dfc7.hot-update.js",
    "/0.04c2947b824c075c9df1.hot-update.js": "/0.04c2947b824c075c9df1.hot-update.js",
    "/0.5c3e27d132e5feed597b.hot-update.js": "/0.5c3e27d132e5feed597b.hot-update.js",
    "/0.0a396dee69e6541b2ad7.hot-update.js": "/0.0a396dee69e6541b2ad7.hot-update.js",
    "/0.d4bbd0271b28b03f6d4f.hot-update.js": "/0.d4bbd0271b28b03f6d4f.hot-update.js",
    "/0.4c16bf81463b880e1bbb.hot-update.js": "/0.4c16bf81463b880e1bbb.hot-update.js",
    "/0.d9a143e857032c7f0578.hot-update.js": "/0.d9a143e857032c7f0578.hot-update.js",
    "/0.59b72e81cdb09e476b64.hot-update.js": "/0.59b72e81cdb09e476b64.hot-update.js",
    "/0.fb68771ad620515dbdd0.hot-update.js": "/0.fb68771ad620515dbdd0.hot-update.js",
    "/0.4edb5cdb587f9f1bb5f3.hot-update.js": "/0.4edb5cdb587f9f1bb5f3.hot-update.js",
    "/0.240f018525825d040656.hot-update.js": "/0.240f018525825d040656.hot-update.js",
    "/0.7290f6c506b41127cb72.hot-update.js": "/0.7290f6c506b41127cb72.hot-update.js",
    "/0.069ae0f00ce5fa469f5c.hot-update.js": "/0.069ae0f00ce5fa469f5c.hot-update.js",
    "/0.7500ec12cf9cc08ce32d.hot-update.js": "/0.7500ec12cf9cc08ce32d.hot-update.js",
    "/0.817210f9ec04692c6733.hot-update.js": "/0.817210f9ec04692c6733.hot-update.js",
    "/0.08c8144581d7f98f320a.hot-update.js": "/0.08c8144581d7f98f320a.hot-update.js",
    "/0.baf1a11c7541cfdc0fb6.hot-update.js": "/0.baf1a11c7541cfdc0fb6.hot-update.js",
    "/0.3499b2386929a49279e4.hot-update.js": "/0.3499b2386929a49279e4.hot-update.js",
    "/0.42ab8efcc89cdbe903fc.hot-update.js": "/0.42ab8efcc89cdbe903fc.hot-update.js",
    "/0.5ff980697241ca7957c1.hot-update.js": "/0.5ff980697241ca7957c1.hot-update.js",
    "/0.04f5ec9938555aa5f7a9.hot-update.js": "/0.04f5ec9938555aa5f7a9.hot-update.js",
    "/0.4c89936401911331d63b.hot-update.js": "/0.4c89936401911331d63b.hot-update.js",
    "/0.f5378b0b21a3a5f41573.hot-update.js": "/0.f5378b0b21a3a5f41573.hot-update.js",
    "/0.9a7e171d5d1ca4d0efcd.hot-update.js": "/0.9a7e171d5d1ca4d0efcd.hot-update.js",
    "/0.184cae0fc3297a057562.hot-update.js": "/0.184cae0fc3297a057562.hot-update.js",
    "/0.811e18bf91613630ae55.hot-update.js": "/0.811e18bf91613630ae55.hot-update.js",
    "/0.1a4c4356dad8562fe355.hot-update.js": "/0.1a4c4356dad8562fe355.hot-update.js",
    "/0.5edc7d2a4d260a1ec682.hot-update.js": "/0.5edc7d2a4d260a1ec682.hot-update.js",
    "/0.e539be8856ef73585791.hot-update.js": "/0.e539be8856ef73585791.hot-update.js",
    "/0.2481df4e32aa7e20a20b.hot-update.js": "/0.2481df4e32aa7e20a20b.hot-update.js",
    "/0.2e7dee5088f858835d37.hot-update.js": "/0.2e7dee5088f858835d37.hot-update.js",
    "/0.76c4afb49a252cf7719d.hot-update.js": "/0.76c4afb49a252cf7719d.hot-update.js",
    "/0.13c84192cd9cb21c8be2.hot-update.js": "/0.13c84192cd9cb21c8be2.hot-update.js",
    "/0.cced3c69e7c2d47adc73.hot-update.js": "/0.cced3c69e7c2d47adc73.hot-update.js",
    "/0.0b3af244bbb5c7cb7a9b.hot-update.js": "/0.0b3af244bbb5c7cb7a9b.hot-update.js",
    "/0.ba71cde58ba946aed2ad.hot-update.js": "/0.ba71cde58ba946aed2ad.hot-update.js",
    "/0.01fddfbd6c9c5d0bec84.hot-update.js": "/0.01fddfbd6c9c5d0bec84.hot-update.js",
    "/0.783a63c8e9cfd49e5607.hot-update.js": "/0.783a63c8e9cfd49e5607.hot-update.js",
    "/0.af6390e40a56805e42aa.hot-update.js": "/0.af6390e40a56805e42aa.hot-update.js",
    "/0.97d3f7989c7e2e92f1af.hot-update.js": "/0.97d3f7989c7e2e92f1af.hot-update.js",
    "/0.e92604b9e5960363a11e.hot-update.js": "/0.e92604b9e5960363a11e.hot-update.js",
    "/0.361f5b886a5539b41122.hot-update.js": "/0.361f5b886a5539b41122.hot-update.js",
    "/0.105ba3cff532bb2bb70d.hot-update.js": "/0.105ba3cff532bb2bb70d.hot-update.js",
    "/0.40d35c9453374afb102c.hot-update.js": "/0.40d35c9453374afb102c.hot-update.js",
    "/0.ddfcf9d4885c5e082b21.hot-update.js": "/0.ddfcf9d4885c5e082b21.hot-update.js",
    "/0.e05a63865c41f324d087.hot-update.js": "/0.e05a63865c41f324d087.hot-update.js",
    "/0.db36f841153ad6bc6d07.hot-update.js": "/0.db36f841153ad6bc6d07.hot-update.js",
    "/0.63b616f4ce97355d79a3.hot-update.js": "/0.63b616f4ce97355d79a3.hot-update.js",
    "/0.4db21c0f95b8b7ee6524.hot-update.js": "/0.4db21c0f95b8b7ee6524.hot-update.js",
    "/0.78582e711067683b1879.hot-update.js": "/0.78582e711067683b1879.hot-update.js",
    "/0.2bc43392e9bfaa9b9b4b.hot-update.js": "/0.2bc43392e9bfaa9b9b4b.hot-update.js",
    "/0.877b86b9ad0d8210fef5.hot-update.js": "/0.877b86b9ad0d8210fef5.hot-update.js",
    "/0.724b0e717c075a7f7096.hot-update.js": "/0.724b0e717c075a7f7096.hot-update.js",
    "/0.cb89aa1a28255a130d76.hot-update.js": "/0.cb89aa1a28255a130d76.hot-update.js",
    "/0.9d33fa2db3a33779f190.hot-update.js": "/0.9d33fa2db3a33779f190.hot-update.js",
    "/0.d85a6b880bde0fa8720b.hot-update.js": "/0.d85a6b880bde0fa8720b.hot-update.js",
    "/0.ca578f929e87f41cc655.hot-update.js": "/0.ca578f929e87f41cc655.hot-update.js",
    "/0.3e86fc1614b0d1d2d524.hot-update.js": "/0.3e86fc1614b0d1d2d524.hot-update.js",
    "/0.319c37d5b5e62f386069.hot-update.js": "/0.319c37d5b5e62f386069.hot-update.js",
    "/0.3a47d60e5d8b476e6a58.hot-update.js": "/0.3a47d60e5d8b476e6a58.hot-update.js",
    "/0.a6bb2e31f1887d6bfd6a.hot-update.js": "/0.a6bb2e31f1887d6bfd6a.hot-update.js",
    "/0.1d4b010126dd6c871146.hot-update.js": "/0.1d4b010126dd6c871146.hot-update.js",
    "/0.7f3c81c0a103d2e630da.hot-update.js": "/0.7f3c81c0a103d2e630da.hot-update.js",
    "/0.ca2de495ff3255b1d9b3.hot-update.js": "/0.ca2de495ff3255b1d9b3.hot-update.js",
    "/0.7d10d243e641e634a85d.hot-update.js": "/0.7d10d243e641e634a85d.hot-update.js",
    "/0.64e518f1d65a7b299a61.hot-update.js": "/0.64e518f1d65a7b299a61.hot-update.js",
    "/0.0c5e279057a6e8ffdcb9.hot-update.js": "/0.0c5e279057a6e8ffdcb9.hot-update.js",
    "/0.2ac7f53add1e67ec8aa4.hot-update.js": "/0.2ac7f53add1e67ec8aa4.hot-update.js",
    "/0.e8cd2eb0b02ccd5a6ea6.hot-update.js": "/0.e8cd2eb0b02ccd5a6ea6.hot-update.js",
    "/0.13290184782ab42a55ad.hot-update.js": "/0.13290184782ab42a55ad.hot-update.js",
    "/0.29f47677c54956d4daf8.hot-update.js": "/0.29f47677c54956d4daf8.hot-update.js"
}